{
  "users": [
    {
      "id": 23,
      "name": "Alejandro Velasquez",
      "email": "alejandrovelasquez@gmail.com",
      "birthdate": "10/12/1994",
      "password": "password123",
      "roleId": 1
    },
    {
      "id": "a75a",
      "name": "alejo",
      "email": "alejo@gmail.com",
      "date": "2004-03-11",
      "password": "123",
      "roleId": 2
    }
  ],
  "booking": [
    {
      "id": "57d0",
      "flightId": null,
      "userId": "a75a",
      "bookingDate": "7/6/2024, 1:06:15 a. m."
    }
  ],
  "flight": [
    {
      "id": "1487",
      "number": "569",
      "origin": "Italia",
      "destination": "Madrid",
      "departure": "2024-06-28",
      "arrival": "2024-06-29",
      "capacity": "100"
    }
  ]
}